[
    {
        "missionTitle": "Super smooth buying process!",
        "subTitle": "Sales process was simple and easy.",
        "missionDiscription": "Got my Honda City from Carosa — transparent, fast, and hassle-free!",
        "person": "Rohit Kumar"
    },
     {
        "missionTitle": "Feels like new!",
        "subTitle": "Sales process was simple and easy.",
        "missionDiscription": "My pre-owned car looks brand new and came with full inspection. Totally worth it!",
        "person": "Akram Ali"
    },
     {
        "missionTitle": "Trustworthy platform.",
        "subTitle": "“Trustworthy platform.” Genuine cars, no hidden charges, and clear documentation. Loved it!",
        "missionDiscription": "Genuine cars, no hidden charges, and clear documentation. Loved it!",
        "person": "Karan"
    },
     {
        "missionTitle": "Great doorstep delivery.",
        "subTitle": "Maximillion was friendly and I didn’t feel...",
        "missionDiscription": "My Creta arrived on time, shining like new. Excellent service!",
        "person": "Yash"
    },
     {
        "missionTitle": "Best used car experience. ",
        "subTitle": "Sales process was simple and easy.",
        "missionDiscription": "Verified, affordable, and professional — Carosa delivers what it promises!",
        "person": "Gufran"
    }
]